multilayer_surface_plasmon.py
setup.py
multilayer_surface_plasmon.egg-info/PKG-INFO
multilayer_surface_plasmon.egg-info/SOURCES.txt
multilayer_surface_plasmon.egg-info/dependency_links.txt
multilayer_surface_plasmon.egg-info/top_level.txt