Metadata-Version: 1.1
Name: multilayer-surface-plasmon
Version: 0.1.2
Summary: Calculates surface-plasmon-polariton modes for planar structures.
Home-page: http://pythonhosted.org/multilayer_surface_plasmon/
Author: Steven Byrnes
Author-email: steven.byrnes@gmail.com
License: MIT
Keywords: optics,electromagnetism,surface plasmon,surface plasmon polariton,transverse magnetic mode,TM mode
Platform: UNKNOWN
Classifier: Development Status :: 4 - Beta
Classifier: Intended Audience :: Science/Research
Classifier: Topic :: Scientific/Engineering
Classifier: Topic :: Scientific/Engineering :: Physics
Classifier: License :: OSI Approved :: MIT License
Classifier: Operating System :: OS Independent
Classifier: Programming Language :: Python :: 2
Classifier: Programming Language :: Python :: 3
